[
  {
    "branch": "г.Тюмень, Первомайская 19",
    "location": "19_105",
    "printer_model": "Xerox Versalink B605",
    "cartridge_color": "Черный",
    "db_name": "ITINVENT",
    "timestamp": "2025-10-21T23:16:42.619647",
    "component_type": "cartridge",
    "component_color": "Черный",
    "model_name": "Xerox Versalink B605"
  },
  {
    "branch": "г.Тюмень, Первомайская 19",
    "location": "19_105",
    "printer_model": "Xerox Versalink B605",
    "cartridge_color": "Черный",
    "db_name": "ITINVENT",
    "timestamp": "2025-10-21T23:16:42.619647"
  },
  {
    "branch": "г.Тюмень, Первомайская 19",
    "location": "19_103",
    "printer_model": "Xerox VersaLink  B405DN MFP",
    "cartridge_color": "Черный",
    "db_name": "ITINVENT",
    "timestamp": "2025-10-28T14:59:12.266240",
    "component_type": "cartridge",
    "component_color": "Черный",
    "model_name": "Xerox VersaLink  B405DN MFP"
  },
  {
    "branch": "г.Тюмень, Первомайская 19",
    "location": "19_103",
    "printer_model": "Xerox VersaLink  B405DN MFP",
    "cartridge_color": "Черный",
    "db_name": "ITINVENT",
    "timestamp": "2025-10-28T14:59:12.266240"
  },
  {
    "branch": "г.Тюмень, Первомайская 19",
    "location": "19_105",
    "printer_model": "Xerox VersaLink C7020 MFP",
    "cartridge_color": "Синий (Cyan)",
    "db_name": "ITINVENT",
    "timestamp": "2025-10-22T09:04:41.906859",
    "component_type": "cartridge",
    "component_color": "Синий (Cyan)",
    "model_name": "Xerox VersaLink C7020 MFP"
  },
  {
    "branch": "г.Тюмень, Первомайская 19",
    "location": "19_105",
    "printer_model": "Xerox VersaLink C7020 MFP",
    "cartridge_color": "Синий (Cyan)",
    "db_name": "ITINVENT",
    "timestamp": "2025-10-22T09:04:41.906859"
  },
  {
    "branch": "г.Тюмень, Первомайская 19",
    "location": "19_304",
    "printer_model": "Xerox Versalink B605",
    "cartridge_color": "Черный",
    "db_name": "ITINVENT",
    "timestamp": "2025-10-22T08:31:42.072752",
    "component_type": "cartridge",
    "component_color": "Черный",
    "model_name": "Xerox Versalink B605"
  },
  {
    "branch": "г.Тюмень, Первомайская 19",
    "location": "19_304",
    "printer_model": "Xerox Versalink B605",
    "cartridge_color": "Черный",
    "db_name": "ITINVENT",
    "timestamp": "2025-10-22T08:31:42.072752"
  },
  {
    "branch": "г.Тюмень, Первомайская 19",
    "location": "19_105",
    "printer_model": "Xerox VersaLink C7020 MFP",
    "cartridge_color": "Черный",
    "db_name": "ITINVENT",
    "timestamp": "2025-10-22T01:02:41.972881",
    "component_type": "cartridge",
    "component_color": "Черный",
    "model_name": "Xerox VersaLink C7020 MFP"
  },
  {
    "branch": "г.Тюмень, Первомайская 19",
    "location": "19_105",
    "printer_model": "Xerox VersaLink C7020 MFP",
    "cartridge_color": "Черный",
    "db_name": "ITINVENT",
    "timestamp": "2025-10-22T01:02:41.972881"
  },
  {
    "branch": "г.Тюмень, Первомайская 19",
    "location": "19_105",
    "printer_model": "xerox versalink c7020 mfp",
    "component_type": "cartridge",
    "component_color": "Желтый (Yellow)",
    "cartridge_model": "",
    "detection_source": "unknown",
    "printer_is_color": true,
    "cartridge_color": "Желтый (Yellow)",
    "db_name": "ITINVENT",
    "timestamp": "2025-12-22T15:48:34.923361",
    "model_name": "xerox versalink c7020 mfp"
  },
  {
    "branch": "г.Тюмень, Первомайская 19",
    "location": "19_105",
    "printer_model": "xerox versalink c7120",
    "component_type": "fuser",
    "component_color": "Универсальный",
    "cartridge_model": "115R00334",
    "detection_source": "test",
    "printer_is_color": true,
    "cartridge_color": "",
    "db_name": "ITINVENT",
    "timestamp": "2025-12-22T17:52:36.241489",
    "model_name": "xerox versalink c7120"
  },
  {
    "branch": "г.Тюмень, Первомайская 19",
    "location": "19_306",
    "printer_model": "HP LaserJet Pro MFP M428dw",
    "component_type": "cartridge",
    "component_color": "Черный",
    "cartridge_model": "HP 59A",
    "detection_source": "database",
    "printer_is_color": false,
    "cartridge_color": "Черный",
    "db_name": "ITINVENT",
    "timestamp": "2026-01-12T11:10:07.864609",
    "model_name": "HP LaserJet Pro MFP M428dw"
  },
  {
    "branch": "г.Тюмень, Первомайская 19",
    "location": "19_306",
    "printer_model": "HP LaserJet Pro MFP M428dw",
    "component_type": "cartridge",
    "component_color": "Черный",
    "cartridge_model": "HP 59A",
    "detection_source": "database",
    "printer_is_color": false,
    "cartridge_color": "Черный",
    "db_name": "ITINVENT",
    "timestamp": "2026-01-12T11:10:07.864609"
  },
  {
    "branch": "г.Тюмень, Первомайская 19",
    "location": "19_301",
    "printer_model": "canon 5236",
    "component_type": "photoconductor",
    "component_color": "Универсальный",
    "cartridge_color": "",
    "db_name": "ITINVENT",
    "timestamp": "2025-12-17T14:18:18.114015",
    "model_name": "canon 5236"
  },
  {
    "branch": "г.Тюмень, Первомайская 19",
    "location": "19_105",
    "printer_model": "xerox versalink c7120",
    "component_type": "fuser",
    "component_color": "Универсальный",
    "cartridge_model": "",
    "detection_source": "unknown",
    "printer_is_color": true,
    "cartridge_color": "",
    "db_name": "ITINVENT",
    "timestamp": "2025-12-22T17:32:28.767455",
    "model_name": "xerox versalink c7120"
  },
  {
    "branch": "г.Тюмень, Первомайская 19",
    "location": "19_105",
    "printer_model": "xerox versalink c7120",
    "component_type": "fuser",
    "component_color": "Универсальный",
    "cartridge_model": "",
    "detection_source": "unknown",
    "printer_is_color": true,
    "cartridge_color": "",
    "db_name": "ITINVENT",
    "timestamp": "2025-12-22T17:32:28.767455"
  },
  {
    "branch": "г.Тюмень, Первомайская 19",
    "location": "7120",
    "printer_model": "xerox versalink c7120",
    "component_type": "fuser",
    "component_color": "Универсальный",
    "cartridge_model": "",
    "detection_source": "unknown",
    "printer_is_color": true,
    "cartridge_color": "",
    "db_name": "ITINVENT",
    "timestamp": "2025-12-22T17:25:51.998273",
    "model_name": "xerox versalink c7120"
  },
  {
    "branch": "г.Тюмень, Первомайская 19",
    "location": "7120",
    "printer_model": "xerox versalink c7120",
    "component_type": "fuser",
    "component_color": "Универсальный",
    "cartridge_model": "",
    "detection_source": "unknown",
    "printer_is_color": true,
    "cartridge_color": "",
    "db_name": "ITINVENT",
    "timestamp": "2025-12-22T17:25:51.998273"
  },
  {
    "branch": "г.Тюмень, Первомайская 19",
    "location": "19_105",
    "printer_model": "Xerox VersaLink C7020 MFP",
    "component_type": "fuser",
    "component_color": "Универсальный",
    "cartridge_model": "",
    "detection_source": "unknown",
    "printer_is_color": true,
    "cartridge_color": "",
    "db_name": "ITINVENT",
    "timestamp": "2025-12-22T17:18:24.350217",
    "model_name": "Xerox VersaLink C7020 MFP"
  },
  {
    "branch": "г.Тюмень, Первомайская 19",
    "location": "19_105",
    "printer_model": "Xerox VersaLink C7020 MFP",
    "component_type": "fuser",
    "component_color": "Универсальный",
    "cartridge_model": "",
    "detection_source": "unknown",
    "printer_is_color": true,
    "cartridge_color": "",
    "db_name": "ITINVENT",
    "timestamp": "2025-12-22T17:18:24.350217"
  },
  {
    "branch": "г.Тюмень, Первомайская 19",
    "location": "19_105",
    "printer_model": "xerox versalink c7120",
    "component_type": "cartridge",
    "component_color": "Желтый (Yellow)",
    "cartridge_model": "Xerox 006R01826",
    "detection_source": "database",
    "printer_is_color": true,
    "cartridge_color": "Желтый (Yellow)",
    "db_name": "ITINVENT",
    "timestamp": "2025-12-22T17:11:03.141890",
    "model_name": "xerox versalink c7120"
  },
  {
    "branch": "г.Тюмень, Первомайская 19",
    "location": "19_105",
    "printer_model": "xerox versalink c7120",
    "component_type": "cartridge",
    "component_color": "Желтый (Yellow)",
    "cartridge_model": "Xerox 006R01826",
    "detection_source": "database",
    "printer_is_color": true,
    "cartridge_color": "Желтый (Yellow)",
    "db_name": "ITINVENT",
    "timestamp": "2025-12-22T17:11:03.141890"
  },
  {
    "branch": "г.Тюмень, Первомайская 19",
    "location": "19_105",
    "printer_model": "Xerox VersaLink C7020 MFP",
    "component_type": "cartridge",
    "component_color": "Пурпурный (Magenta)",
    "cartridge_model": "Xerox 006R01637",
    "detection_source": "database",
    "printer_is_color": true,
    "cartridge_color": "Пурпурный (Magenta)",
    "db_name": "ITINVENT",
    "timestamp": "2025-12-22T16:56:39.782134",
    "model_name": "Xerox VersaLink C7020 MFP"
  },
  {
    "branch": "г.Тюмень, Первомайская 19",
    "location": "19_105",
    "printer_model": "Xerox VersaLink C7020 MFP",
    "component_type": "cartridge",
    "component_color": "Пурпурный (Magenta)",
    "cartridge_model": "Xerox 006R01637",
    "detection_source": "database",
    "printer_is_color": true,
    "cartridge_color": "Пурпурный (Magenta)",
    "db_name": "ITINVENT",
    "timestamp": "2025-12-22T16:56:39.782134"
  },
  {
    "branch": "г.Тюмень, Первомайская 19",
    "location": "19_105",
    "printer_model": "Xerox VersaLink C7020 MFP",
    "component_type": "cartridge",
    "component_color": "Желтый (Yellow)",
    "cartridge_model": "Xerox 006R01640",
    "detection_source": "database",
    "printer_is_color": true,
    "cartridge_color": "Желтый (Yellow)",
    "db_name": "ITINVENT",
    "timestamp": "2025-12-22T16:25:14.507751",
    "model_name": "Xerox VersaLink C7020 MFP"
  },
  {
    "branch": "г.Тюмень, Первомайская 19",
    "location": "19_105",
    "printer_model": "Xerox VersaLink C7020 MFP",
    "component_type": "cartridge",
    "component_color": "Желтый (Yellow)",
    "cartridge_model": "Xerox 006R01640",
    "detection_source": "database",
    "printer_is_color": true,
    "cartridge_color": "Желтый (Yellow)",
    "db_name": "ITINVENT",
    "timestamp": "2025-12-22T16:25:14.507751"
  },
  {
    "branch": "г.Тюмень, Первомайская 19",
    "location": "19_105",
    "printer_model": "Xerox VersaLink C7020 MFP",
    "component_type": "cartridge",
    "component_color": "Желтый (Yellow)",
    "cartridge_model": "",
    "detection_source": "unknown",
    "printer_is_color": true,
    "cartridge_color": "Желтый (Yellow)",
    "db_name": "ITINVENT",
    "timestamp": "2025-12-22T16:12:50.838479",
    "model_name": "Xerox VersaLink C7020 MFP"
  },
  {
    "branch": "г.Тюмень, Первомайская 19",
    "location": "19_105",
    "printer_model": "Xerox VersaLink C7020 MFP",
    "component_type": "cartridge",
    "component_color": "Желтый (Yellow)",
    "cartridge_model": "",
    "detection_source": "unknown",
    "printer_is_color": true,
    "cartridge_color": "Желтый (Yellow)",
    "db_name": "ITINVENT",
    "timestamp": "2025-12-22T16:12:50.838479"
  },
  {
    "branch": "г.Тюмень, Первомайская 19",
    "location": "19_101",
    "printer_model": "Canon Sensys MF428x",
    "component_type": "cartridge",
    "component_color": "Черный",
    "cartridge_model": "Canon 052",
    "detection_source": "database",
    "printer_is_color": false,
    "cartridge_color": "Черный",
    "db_name": "ITINVENT",
    "timestamp": "2026-01-29T11:57:13.124301",
    "model_name": "Canon Sensys MF428x"
  },
  {
    "branch": "г.Тюмень, Первомайская 19",
    "location": "19_101",
    "printer_model": "Canon Sensys MF428x",
    "component_type": "cartridge",
    "component_color": "Черный",
    "cartridge_model": "Canon 052",
    "detection_source": "database",
    "printer_is_color": false,
    "cartridge_color": "Черный",
    "db_name": "ITINVENT",
    "timestamp": "2026-01-29T11:57:13.124301"
  },
  {
    "branch": "г.Тюмень, Первомайская 19",
    "location": "19_102",
    "printer_model": "HP LaserJet 1536dnf MFP",
    "component_type": "cartridge",
    "component_color": "Черный",
    "cartridge_model": "",
    "detection_source": "unknown",
    "printer_is_color": false,
    "cartridge_color": "Черный",
    "db_name": "ITINVENT",
    "timestamp": "2025-12-23T14:59:59.023968",
    "model_name": "HP LaserJet 1536dnf MFP"
  },
  {
    "branch": "г.Тюмень, Первомайская 19",
    "location": "19_102",
    "printer_model": "HP LaserJet 1536dnf MFP",
    "component_type": "cartridge",
    "component_color": "Черный",
    "cartridge_model": "",
    "detection_source": "unknown",
    "printer_is_color": false,
    "cartridge_color": "Черный",
    "db_name": "ITINVENT",
    "timestamp": "2025-12-23T14:59:59.023968"
  },
  {
    "branch": "г.Тюмень, Первомайская 19",
    "location": "19_105",
    "printer_model": "xerox versalink c7020 mfp",
    "component_type": "photoconductor",
    "component_color": "Универсальный",
    "cartridge_model": "113R00780",
    "detection_source": "unknown",
    "printer_is_color": true,
    "cartridge_color": "",
    "db_name": "ITINVENT",
    "timestamp": "2025-12-22T17:54:30.947320",
    "model_name": "xerox versalink c7020 mfp"
  },
  {
    "branch": "г.Тюмень, Первомайская 19",
    "location": "19_105",
    "printer_model": "xerox versalink c7020 mfp",
    "component_type": "photoconductor",
    "component_color": "Универсальный",
    "cartridge_model": "113R00780",
    "detection_source": "unknown",
    "printer_is_color": true,
    "cartridge_color": "",
    "db_name": "ITINVENT",
    "timestamp": "2025-12-22T17:54:30.947320"
  },
  {
    "branch": "г.Тюмень, Первомайская 19",
    "location": "19_105",
    "printer_model": "xerox versalink c7120",
    "component_type": "fuser",
    "component_color": "Универсальный",
    "cartridge_model": "115R00334",
    "detection_source": "unknown",
    "printer_is_color": true,
    "cartridge_color": "",
    "db_name": "ITINVENT",
    "timestamp": "2025-12-22T17:53:53.774861",
    "model_name": "xerox versalink c7120"
  },
  {
    "branch": "г.Тюмень, Первомайская 19",
    "location": "19_105",
    "printer_model": "xerox versalink c7120",
    "component_type": "fuser",
    "component_color": "Универсальный",
    "cartridge_model": "115R00334",
    "detection_source": "unknown",
    "printer_is_color": true,
    "cartridge_color": "",
    "db_name": "ITINVENT",
    "timestamp": "2025-12-22T17:53:53.774861"
  },
  {
    "branch": "г.Тюмень, Первомайская 21",
    "location": "Холл 1 эт.",
    "printer_model": "Xerox VersaLink C7020 MFP",
    "cartridge_color": "Желтый (Yellow)",
    "db_name": "ITINVENT",
    "timestamp": "2025-12-08T11:57:12.772622",
    "component_type": "cartridge",
    "component_color": "Желтый (Yellow)",
    "model_name": "Xerox VersaLink C7020 MFP"
  },
  {
    "branch": "г.Тюмень, Первомайская 21",
    "location": "Холл 1 эт.",
    "printer_model": "Xerox VersaLink C7020 MFP",
    "cartridge_color": "Желтый (Yellow)",
    "db_name": "ITINVENT",
    "timestamp": "2025-12-08T11:57:12.772622"
  },
  {
    "branch": "г.Тюмень, Первомайская 21",
    "location": "Холл 1 эт.",
    "printer_model": "Xerox VersaLink C7020 MFP",
    "cartridge_color": "Пурпурный (Magenta)",
    "db_name": "ITINVENT",
    "timestamp": "2025-12-08T11:56:32.253290",
    "component_type": "cartridge",
    "component_color": "Пурпурный (Magenta)",
    "model_name": "Xerox VersaLink C7020 MFP"
  },
  {
    "branch": "г.Тюмень, Первомайская 21",
    "location": "Холл 1 эт.",
    "printer_model": "Xerox VersaLink C7020 MFP",
    "cartridge_color": "Пурпурный (Magenta)",
    "db_name": "ITINVENT",
    "timestamp": "2025-12-08T11:56:32.253290"
  },
  {
    "branch": "г.Тюмень, Первомайская 21",
    "location": "21_102",
    "printer_model": "Xerox VersaLink C7020 MFP",
    "cartridge_color": "Желтый (Yellow)",
    "db_name": "ITINVENT",
    "timestamp": "2025-12-08T11:55:44.074782",
    "component_type": "cartridge",
    "component_color": "Желтый (Yellow)",
    "model_name": "Xerox VersaLink C7020 MFP"
  },
  {
    "branch": "г.Тюмень, Первомайская 21",
    "location": "21_102",
    "printer_model": "Xerox VersaLink C7020 MFP",
    "cartridge_color": "Желтый (Yellow)",
    "db_name": "ITINVENT",
    "timestamp": "2025-12-08T11:55:44.074782"
  },
  {
    "branch": "г.Тюмень, Первомайская 19",
    "location": "19_302",
    "printer_model": "Xerox VersaLink C7020 MFP",
    "cartridge_color": "Желтый (Yellow)",
    "db_name": "ITINVENT",
    "timestamp": "2025-12-01T11:52:11.416243",
    "component_type": "cartridge",
    "component_color": "Желтый (Yellow)",
    "model_name": "Xerox VersaLink C7020 MFP"
  },
  {
    "branch": "г.Тюмень, Первомайская 19",
    "location": "19_302",
    "printer_model": "Xerox VersaLink C7020 MFP",
    "cartridge_color": "Желтый (Yellow)",
    "db_name": "ITINVENT",
    "timestamp": "2025-12-01T11:52:11.416243"
  },
  {
    "branch": "г.Тюмень, Первомайская 21",
    "location": "21_101",
    "printer_model": "Color LaserJet Pro MFP M479dw",
    "cartridge_color": "Пурпурный (Magenta)",
    "db_name": "ITINVENT",
    "timestamp": "2025-11-21T11:53:45.078703",
    "component_type": "cartridge",
    "component_color": "Пурпурный (Magenta)",
    "model_name": "Color LaserJet Pro MFP M479dw"
  },
  {
    "branch": "г.Тюмень, Первомайская 21",
    "location": "21_101",
    "printer_model": "Color LaserJet Pro MFP M479dw",
    "cartridge_color": "Пурпурный (Magenta)",
    "db_name": "ITINVENT",
    "timestamp": "2025-11-21T11:53:45.078703"
  },
  {
    "branch": "г.Тюмень, Первомайская 21",
    "location": "21_205",
    "printer_model": "МФУ Kyocera EcoSys M5526cdn",
    "cartridge_color": "Синий (Cyan)",
    "db_name": "ITINVENT",
    "timestamp": "2025-11-21T11:45:19.642315",
    "component_type": "cartridge",
    "component_color": "Синий (Cyan)",
    "model_name": "МФУ Kyocera EcoSys M5526cdn"
  },
  {
    "branch": "г.Тюмень, Первомайская 21",
    "location": "21_205",
    "printer_model": "МФУ Kyocera EcoSys M5526cdn",
    "cartridge_color": "Синий (Cyan)",
    "db_name": "ITINVENT",
    "timestamp": "2025-11-21T11:45:19.642315"
  },
  {
    "branch": "г.Тюмень, Первомайская 21",
    "location": "21_205",
    "printer_model": "МФУ Kyocera EcoSys M5526cdn",
    "cartridge_color": "Желтый (Yellow)",
    "db_name": "ITINVENT",
    "timestamp": "2025-11-21T11:43:14.608429",
    "component_type": "cartridge",
    "component_color": "Желтый (Yellow)",
    "model_name": "МФУ Kyocera EcoSys M5526cdn"
  },
  {
    "branch": "г.Тюмень, Первомайская 21",
    "location": "21_205",
    "printer_model": "МФУ Kyocera EcoSys M5526cdn",
    "cartridge_color": "Желтый (Yellow)",
    "db_name": "ITINVENT",
    "timestamp": "2025-11-21T11:43:14.608429"
  },
  {
    "branch": "г.Тюмень, Первомайская 21",
    "location": "21_205",
    "printer_model": "МФУ Kyocera EcoSys M5526cdn",
    "cartridge_color": "Пурпурный (Magenta)",
    "db_name": "ITINVENT",
    "timestamp": "2025-11-21T11:42:46.346725",
    "component_type": "cartridge",
    "component_color": "Пурпурный (Magenta)",
    "model_name": "МФУ Kyocera EcoSys M5526cdn"
  },
  {
    "branch": "г.Тюмень, Первомайская 21",
    "location": "21_205",
    "printer_model": "МФУ Kyocera EcoSys M5526cdn",
    "cartridge_color": "Пурпурный (Magenta)",
    "db_name": "ITINVENT",
    "timestamp": "2025-11-21T11:42:46.346725"
  },
  {
    "branch": "г.Тюмень, Первомайская 19",
    "location": "19_204/1",
    "printer_model": "HP Color LaserJet Pro M479fnw",
    "cartridge_color": "Синий (Cyan)",
    "db_name": "ITINVENT",
    "timestamp": "2025-11-21T11:36:49.034473",
    "component_type": "cartridge",
    "component_color": "Синий (Cyan)",
    "model_name": "HP Color LaserJet Pro M479fnw"
  },
  {
    "branch": "г.Тюмень, Первомайская 19",
    "location": "19_204/1",
    "printer_model": "HP Color LaserJet Pro M479fnw",
    "cartridge_color": "Синий (Cyan)",
    "db_name": "ITINVENT",
    "timestamp": "2025-11-21T11:36:49.034473"
  },
  {
    "branch": "г.Тюмень, Первомайская 19",
    "location": "19_204/1",
    "printer_model": "HP Color LaserJet Pro M479fnw",
    "cartridge_color": "Желтый (Yellow)",
    "db_name": "ITINVENT",
    "timestamp": "2025-11-21T11:35:53.854592",
    "component_type": "cartridge",
    "component_color": "Желтый (Yellow)",
    "model_name": "HP Color LaserJet Pro M479fnw"
  },
  {
    "branch": "г.Тюмень, Первомайская 19",
    "location": "19_204/1",
    "printer_model": "HP Color LaserJet Pro M479fnw",
    "cartridge_color": "Желтый (Yellow)",
    "db_name": "ITINVENT",
    "timestamp": "2025-11-21T11:35:53.854592"
  },
  {
    "branch": "г.Тюмень, Первомайская 19",
    "location": "19_204/1",
    "printer_model": "HP Color LaserJet Pro M479fnw",
    "cartridge_color": "Пурпурный (Magenta)",
    "db_name": "ITINVENT",
    "timestamp": "2025-11-21T11:35:23.149371",
    "component_type": "cartridge",
    "component_color": "Пурпурный (Magenta)",
    "model_name": "HP Color LaserJet Pro M479fnw"
  },
  {
    "branch": "г.Тюмень, Первомайская 19",
    "location": "19_204/1",
    "printer_model": "HP Color LaserJet Pro M479fnw",
    "cartridge_color": "Пурпурный (Magenta)",
    "db_name": "ITINVENT",
    "timestamp": "2025-11-21T11:35:23.149371"
  },
  {
    "branch": "г.Тюмень, Первомайская 21",
    "location": "21_101",
    "printer_model": "HP LaserJet Pro MFP M428dw",
    "cartridge_color": "Черный",
    "db_name": "ITINVENT",
    "timestamp": "2025-11-21T11:29:36.324711",
    "component_type": "cartridge",
    "component_color": "Черный",
    "model_name": "HP LaserJet Pro MFP M428dw"
  },
  {
    "branch": "г.Тюмень, Первомайская 21",
    "location": "21_101",
    "printer_model": "HP LaserJet Pro MFP M428dw",
    "cartridge_color": "Черный",
    "db_name": "ITINVENT",
    "timestamp": "2025-11-21T11:29:36.324711"
  },
  {
    "branch": "г.Тюмень, Первомайская 21",
    "location": "Холл 1 эт.",
    "printer_model": "Xerox VersaLink C7020 MFP",
    "cartridge_color": "Пурпурный (Magenta)",
    "db_name": "ITINVENT",
    "timestamp": "2025-11-10T17:26:15.152832",
    "component_type": "cartridge",
    "component_color": "Пурпурный (Magenta)",
    "model_name": "Xerox VersaLink C7020 MFP"
  },
  {
    "branch": "г.Тюмень, Первомайская 21",
    "location": "Холл 1 эт.",
    "printer_model": "Xerox VersaLink C7020 MFP",
    "cartridge_color": "Пурпурный (Magenta)",
    "db_name": "ITINVENT",
    "timestamp": "2025-11-10T17:26:15.152832"
  },
  {
    "branch": "г.Тюмень, Первомайская 21",
    "location": "Холл 1 эт.",
    "printer_model": "Xerox VersaLink C7020 MFP",
    "cartridge_color": "Желтый (Yellow)",
    "db_name": "ITINVENT",
    "timestamp": "2025-11-10T17:24:54.624303",
    "component_type": "cartridge",
    "component_color": "Желтый (Yellow)",
    "model_name": "Xerox VersaLink C7020 MFP"
  },
  {
    "branch": "г.Тюмень, Первомайская 21",
    "location": "Холл 1 эт.",
    "printer_model": "Xerox VersaLink C7020 MFP",
    "cartridge_color": "Желтый (Yellow)",
    "db_name": "ITINVENT",
    "timestamp": "2025-11-10T17:24:54.624303"
  },
  {
    "branch": "г.Тюмень, Первомайская 21",
    "location": "Холл 1 эт.",
    "printer_model": "Xerox VersaLink C7020 MFP",
    "cartridge_color": "Синий (Cyan)",
    "db_name": "ITINVENT",
    "timestamp": "2025-11-10T17:23:51.028018",
    "component_type": "cartridge",
    "component_color": "Синий (Cyan)",
    "model_name": "Xerox VersaLink C7020 MFP"
  },
  {
    "branch": "г.Тюмень, Первомайская 21",
    "location": "Холл 1 эт.",
    "printer_model": "Xerox VersaLink C7020 MFP",
    "cartridge_color": "Синий (Cyan)",
    "db_name": "ITINVENT",
    "timestamp": "2025-11-10T17:23:51.028018"
  },
  {
    "ID": 1317,
    "SERIAL_NO": "3B2120X64108",
    "HW_SERIAL_NO": null,
    "INV_NO": 101318.0,
    "PART_NO": null,
    "CI_TYPE": 1,
    "TYPE_NAME": "ИБП",
    "MODEL_NO": 74,
    "MODEL_NAME": "APC BC750-RS",
    "MANUFACTURER": "APC",
    "LOCATION": "21_207",
    "EMPL_NO": 1991,
    "EMPLOYEE_NAME": "Лупенков Алексей Владимирович",
    "EMPLOYEE_DEPT": "Служба корпоративной защиты",
    "BRANCH_NAME": "г.Тюмень, Первомайская 21",
    "STATUS": "Работает",
    "DESCRIPTION": "Акт 285 Лупенков А.В. 23.08.2023",
    "db_name": "ITINVENT",
    "branch": "г.Тюмень, Первомайская 19",
    "location": "19_105"
  },
  {
    "ID": 3009,
    "SERIAL_NO": "UHB2322030859",
    "HW_SERIAL_NO": null,
    "INV_NO": 103012.0,
    "PART_NO": "ЦБ-00151604",
    "CI_TYPE": 1,
    "TYPE_NAME": "Монитор",
    "MODEL_NO": 93,
    "MODEL_NAME": "Philips 243V7QDSB/01",
    "MANUFACTURER": "Philips",
    "LOCATION": "21_100/1",
    "EMPL_NO": 2630,
    "EMPLOYEE_NAME": "Левицкий Александр Степанович",
    "EMPLOYEE_DEPT": "Управление связи и автоматизации",
    "BRANCH_NAME": "г.Тюмень, Первомайская 21",
    "STATUS": "Работает",
    "DESCRIPTION": "Акт 706 Левин Н Ф.- Левицкий А.С. от 20.01.2026 \r\nTMN-ENG-0069\r\nЦБ-00151604",
    "db_name": "ITINVENT",
    "branch": "г.Тюмень, Первомайская 19",
    "location": "19_304"
  },
  {
    "ID": 3645,
    "SERIAL_NO": "120801136400452",
    "HW_SERIAL_NO": null,
    "INV_NO": 156925.0,
    "PART_NO": null,
    "CI_TYPE": 1,
    "TYPE_NAME": "Системный блок",
    "MODEL_NO": 45,
    "MODEL_NAME": "СКАТ",
    "MANUFACTURER": "Арсенал+",
    "LOCATION": "19_304",
    "EMPL_NO": 3311,
    "EMPLOYEE_NAME": "Хмелевская Анна Сергеевна",
    "EMPLOYEE_DEPT": "Правовое управление",
    "BRANCH_NAME": "г.Тюмень, Первомайская 19",
    "STATUS": "Работает",
    "DESCRIPTION": "Акт 333  передачи Хмелевская А.С. 01.10.2025\r\nАкт аннулирован 331 Кочкина-Загорская от 25.09.2025\r\nнаклейка на системном блоке 1622A003600277",
    "db_name": "ITINVENT",
    "branch": "г.Тюмень, Первомайская 19",
    "location": "19_304"
  },
  {
    "ID": 214,
    "SERIAL_NO": "HAB2209150694",
    "HW_SERIAL_NO": null,
    "INV_NO": 100214.0,
    "PART_NO": null,
    "CI_TYPE": 1,
    "TYPE_NAME": "Системный блок",
    "MODEL_NO": 87,
    "MODEL_NAME": "СКАТ (клавиатура, мышь, сетевой фильтр)",
    "MANUFACTURER": "СКАТ",
    "LOCATION": "19_304",
    "EMPL_NO": 1942,
    "EMPLOYEE_NAME": "Первушина Светлана Владимировна",
    "EMPLOYEE_DEPT": "Правовое управление",
    "BRANCH_NAME": "г.Тюмень, Первомайская 19",
    "STATUS": "Работает",
    "DESCRIPTION": "Акт 356 Айкина В.Г. - Первушина С.В, 15.09.2025\r\nАкт 300 Айкина В.Г. 08.09.2025\r\nПеремещение от уволенного сотрудника с Первомайской, 21 каб.104 (08.09.2025)",
    "db_name": "ITINVENT",
    "branch": "г.Тюмень, Первомайская 19",
    "location": "19_304"
  },
  {
    "ID": 2558,
    "SERIAL_NO": "305RAET9C644",
    "HW_SERIAL_NO": null,
    "INV_NO": 102561.0,
    "PART_NO": "С0000033208",
    "CI_TYPE": 1,
    "TYPE_NAME": "Монитор",
    "MODEL_NO": 457,
    "MODEL_NAME": "LG 24EA53VQ-PA",
    "MANUFACTURER": "LG",
    "LOCATION": "19_304",
    "EMPL_NO": 1543,
    "EMPLOYEE_NAME": "Кремис Мария Витальевна",
    "EMPLOYEE_DEPT": "Правовое управление",
    "BRANCH_NAME": "г.Тюмень, Первомайская 19",
    "STATUS": "Работает",
    "DESCRIPTION": "Акт 655 Мурзакимова Г. Кремис М. от 29.12.2025\r\nTMN-LAW-0073\r\nС0000033208",
    "db_name": "ITINVENT",
    "branch": "г.Тюмень, Первомайская 19",
    "location": "19_307"
  },
  {
    "ID": 1597,
    "SERIAL_NO": "305RAMM9C643",
    "HW_SERIAL_NO": null,
    "INV_NO": 101598.0,
    "PART_NO": null,
    "CI_TYPE": 1,
    "TYPE_NAME": "Монитор",
    "MODEL_NO": 457,
    "MODEL_NAME": "LG 24EA53VQ-PA",
    "MANUFACTURER": "LG",
    "LOCATION": "19_304",
    "EMPL_NO": 1543,
    "EMPLOYEE_NAME": "Кремис Мария Витальевна",
    "EMPLOYEE_DEPT": "Правовое управление",
    "BRANCH_NAME": "г.Тюмень, Первомайская 19",
    "STATUS": "Работает",
    "DESCRIPTION": "Акт 655 Мурзакимова Г. Кремис М. от 29.12.2025\r\nTMN-LAW-0073",
    "db_name": "ITINVENT",
    "branch": "г.Тюмень, Первомайская 19",
    "location": "19_307"
  },
  {
    "ID": 3682,
    "SERIAL_NO": "531809416",
    "HW_SERIAL_NO": null,
    "INV_NO": 156962.0,
    "PART_NO": null,
    "CI_TYPE": 1,
    "TYPE_NAME": "Системный блок",
    "MODEL_NO": 77,
    "MODEL_NAME": "СКАТ",
    "MANUFACTURER": "СКАТ",
    "LOCATION": "19_304",
    "EMPL_NO": 1543,
    "EMPLOYEE_NAME": "Кремис Мария Витальевна",
    "EMPLOYEE_DEPT": "Правовое управление",
    "BRANCH_NAME": "г.Тюмень, Первомайская 19",
    "STATUS": "Работает",
    "DESCRIPTION": "Акт 655 Мурзакимова Г. Кремис М. от 29.12.2025\r\nНепонятно с чьего подотчета взят, установлен взамен вышедшего из строя",
    "db_name": "ITINVENT",
    "branch": "г.Тюмень, Первомайская 19",
    "location": "19_307"
  },
  {
    "ID": 89,
    "SERIAL_NO": "UK0A2034022543",
    "HW_SERIAL_NO": null,
    "INV_NO": 100089.0,
    "PART_NO": null,
    "CI_TYPE": 1,
    "TYPE_NAME": "Монитор",
    "MODEL_NO": 64,
    "MODEL_NAME": "Philips 243V5QHSBA/01",
    "MANUFACTURER": "Philips",
    "LOCATION": "19_205",
    "EMPL_NO": 1528,
    "EMPLOYEE_NAME": "Садыкова Рушания Талиповна",
    "EMPLOYEE_DEPT": "Руководство",
    "BRANCH_NAME": "г.Тюмень, Первомайская 19",
    "STATUS": "Работает",
    "DESCRIPTION": "Акт 632 Коновалов А.С.-Цвигун О.С. от 17.12.2025\r\nАкт 620 Коновалов А.С. от 12.12.2025\r\nАкт 304 Айкина ВГ - Кубарьковой И.Д. 09.09.2025\r\nПередали от уволенного сотрудника СУП в ФЭУ Карташевой Е.\r\nбыл подключен TMN-PTO-0014",
    "db_name": "ITINVENT",
    "branch": "г.Тюмень, Первомайская 19",
    "location": "19_105"
  },
  {
    "serial_no": "PCOUAPVM",
    "hw_serial_no": null,
    "model_name": "ThinkCentre",
    "manufacturer": null,
    "branch": "г.Тюмень, Первомайская 19",
    "location": "19_101",
    "employee": "Пащенко Анастасия Владимировна",
    "inv_no": "156974.0",
    "db_name": "ITINVENT",
    "timestamp": "2026-01-29T10:56:50.929855",
    "serial_number": "PCOUAPVM"
  },
  {
    "serial_no": "PCOUAPVM",
    "hw_serial_no": null,
    "model_name": "ThinkCentre",
    "manufacturer": null,
    "branch": "г.Тюмень, Первомайская 19",
    "location": "19_101",
    "employee": "Пащенко Анастасия Владимировна",
    "inv_no": 156974.0,
    "db_name": "ITINVENT",
    "timestamp": "2026-01-29T10:56:50.929855"
  },
  {
    "branch": "г.Тюмень, Первомайская 21",
    "location": "Холл 1 эт.",
    "printer_model": "Xerox 7020",
    "cartridge_color": "Синий (Cyan)",
    "db_name": "ITINVENT",
    "timestamp": "2025-11-10T17:22:26.843051",
    "component_type": "cartridge",
    "component_color": "Синий (Cyan)",
    "model_name": "Xerox 7020"
  },
  {
    "ID": 3008,
    "SERIAL_NO": "UHB2322032150",
    "HW_SERIAL_NO": null,
    "INV_NO": 103011.0,
    "PART_NO": "ЦБ-00151604",
    "CI_TYPE": 1,
    "TYPE_NAME": "Монитор",
    "MODEL_NO": 93,
    "MODEL_NAME": "Philips 243V7QDSB/01",
    "MANUFACTURER": "Philips",
    "LOCATION": "21_100/1",
    "EMPL_NO": 2630,
    "EMPLOYEE_NAME": "Левицкий Александр Степанович",
    "EMPLOYEE_DEPT": "Управление связи и автоматизации",
    "BRANCH_NAME": "г.Тюмень, Первомайская 21",
    "STATUS": "Работает",
    "DESCRIPTION": "Акт 706 Левин Н Ф.- Левицкий А.С. от 20.01.2026 \r\nTMN-ENG-0069\r\nЦБ-00151604",
    "db_name": "ITINVENT",
    "branch": "г.Тюмень, Первомайская 19",
    "location": "19_304"
  },
  {
    "serial_no": "PC1L1SV7",
    "hw_serial_no": null,
    "model_name": "Lenovo ThinkCentre M75q-1",
    "manufacturer": "Lenovo",
    "branch": "г.Тюмень, Первомайская 19",
    "location": "19_206",
    "employee": "Белослудцев Андрей Николаевич",
    "inv_no": "100715.0",
    "db_name": "ITINVENT",
    "timestamp": "2026-02-17T14:15:51.836013",
    "serial_number": "PC1L1SV7"
  },
  {
    "serial_no": "PC1L1SV7",
    "hw_serial_no": null,
    "model_name": "Lenovo ThinkCentre M75q-1",
    "manufacturer": "Lenovo",
    "branch": "г.Тюмень, Первомайская 19",
    "location": "19_206",
    "employee": "Белослудцев Андрей Николаевич",
    "inv_no": 100715.0,
    "db_name": "ITINVENT",
    "timestamp": "2026-02-17T14:15:51.836013"
  },
  {
    "serial_no": "czc7448jvy",
    "hw_serial_no": null,
    "model_name": "HP ProDesk 400 G4 SFF",
    "manufacturer": "HP",
    "branch": "г.Тюмень, Первомайская 19",
    "location": "19_307",
    "employee": "Шевченко Екатерина Анатольевна",
    "inv_no": "102833.0",
    "db_name": "ITINVENT",
    "timestamp": "2026-02-18T14:38:33.638214",
    "serial_number": "czc7448jvy"
  },
  {
    "serial_no": "czc7448jvy",
    "hw_serial_no": null,
    "model_name": "HP ProDesk 400 G4 SFF",
    "manufacturer": "HP",
    "branch": "г.Тюмень, Первомайская 19",
    "location": "19_307",
    "employee": "Шевченко Екатерина Анатольевна",
    "inv_no": 102833.0,
    "db_name": "ITINVENT",
    "timestamp": "2026-02-18T14:38:33.638214"
  },
  {
    "serial_no": "068060",
    "hw_serial_no": null,
    "model_name": "SKAT",
    "manufacturer": "СКАТ",
    "branch": "г.Тюмень, Первомайская 19",
    "location": "19_206",
    "employee": "Рукшинская Ксения Евгеньевна",
    "inv_no": "100625.0",
    "db_name": "ITINVENT",
    "timestamp": "2026-02-17T14:14:19.989846",
    "serial_number": "068060"
  },
  {
    "serial_no": "4CE947203N",
    "hw_serial_no": null,
    "model_name": "HP ProDesk",
    "manufacturer": "HP",
    "branch": "г.Тюмень, Первомайская 19",
    "location": "19_103",
    "employee": "Марченко Екатерина Николаевна",
    "inv_no": "100810.0",
    "db_name": "ITINVENT",
    "timestamp": "2026-01-28T17:20:58.465883",
    "serial_number": "4CE947203N"
  },
  {
    "serial_no": "PC25JA5F",
    "hw_serial_no": null,
    "model_name": "Lenovo ThinkCentre M720q",
    "manufacturer": "Lenovo",
    "branch": "г.Тюмень, Первомайская 19",
    "location": "19_103",
    "employee": "Тихонова Марина Александровна",
    "inv_no": "100826.0",
    "db_name": "ITINVENT",
    "timestamp": "2026-01-28T13:35:45.630168",
    "serial_number": "PC25JA5F"
  },
  {
    "serial_no": "00125246",
    "hw_serial_no": null,
    "model_name": "СКАТ",
    "manufacturer": "Арсенал+",
    "branch": "г.Тюмень, Первомайская 19",
    "location": "19_307",
    "employee": "Братынкина Валерия Алексеевна",
    "inv_no": "103156.0",
    "db_name": "ITINVENT",
    "timestamp": "2026-02-18T14:37:52.047246",
    "serial_number": "00125246"
  },
  {
    "serial_no": "00125246",
    "hw_serial_no": null,
    "model_name": "СКАТ",
    "manufacturer": "Арсенал+",
    "branch": "г.Тюмень, Первомайская 19",
    "location": "19_307",
    "employee": "Братынкина Валерия Алексеевна",
    "inv_no": 103156.0,
    "db_name": "ITINVENT",
    "timestamp": "2026-02-18T14:37:52.047246"
  },
  {
    "serial_no": "00143665",
    "hw_serial_no": null,
    "model_name": "СКАТ (клавиатура и мышь)",
    "manufacturer": "СКАТ",
    "branch": "г.Тюмень, Первомайская 19",
    "location": "19_206",
    "employee": "Захарова Любовь Юрьевна",
    "inv_no": "100353.0",
    "db_name": "ITINVENT",
    "timestamp": "2026-02-18T14:39:22.156198",
    "serial_number": "00143665"
  },
  {
    "serial_no": "00143665",
    "hw_serial_no": null,
    "model_name": "СКАТ (клавиатура и мышь)",
    "manufacturer": "СКАТ",
    "branch": "г.Тюмень, Первомайская 19",
    "location": "19_206",
    "employee": "Захарова Любовь Юрьевна",
    "inv_no": 100353.0,
    "db_name": "ITINVENT",
    "timestamp": "2026-02-18T14:39:22.156198"
  },
  {
    "serial_no": "FGMLV03",
    "hw_serial_no": null,
    "model_name": "Dell OptiPlex 3070",
    "manufacturer": "Dell",
    "branch": "г.Тюмень, Первомайская 19",
    "location": "19_307",
    "employee": "Атаманова Ольга Юрьевна",
    "inv_no": "102806.0",
    "db_name": "ITINVENT",
    "timestamp": "2026-02-18T14:38:07.132299",
    "serial_number": "FGMLV03"
  },
  {
    "serial_no": "FGMLV03",
    "hw_serial_no": null,
    "model_name": "Dell OptiPlex 3070",
    "manufacturer": "Dell",
    "branch": "г.Тюмень, Первомайская 19",
    "location": "19_307",
    "employee": "Атаманова Ольга Юрьевна",
    "inv_no": 102806.0,
    "db_name": "ITINVENT",
    "timestamp": "2026-02-18T14:38:07.132299"
  },
  {
    "branch": "г.Тюмень, Первомайская 19",
    "location": "19_109",
    "printer_model": "Canon imageRUNNER C3025i",
    "component_type": "cartridge",
    "component_color": "Черный",
    "cartridge_model": "Canon C-EXV 54 Black",
    "detection_source": "database",
    "printer_is_color": true,
    "cartridge_color": "Черный",
    "db_name": "ITINVENT",
    "timestamp": "2026-02-18T14:32:46.027402",
    "model_name": "Canon imageRUNNER C3025i"
  },
  {
    "branch": "г.Тюмень, Первомайская 19",
    "location": "19_109",
    "printer_model": "Canon imageRUNNER C3025i",
    "component_type": "cartridge",
    "component_color": "Черный",
    "cartridge_model": "Canon C-EXV 54 Black",
    "detection_source": "database",
    "printer_is_color": true,
    "cartridge_color": "Черный",
    "db_name": "ITINVENT",
    "timestamp": "2026-02-18T14:32:46.027402"
  },
  {
    "branch": "г.Тюмень, Первомайская 21",
    "location": "21_205",
    "printer_model": "МФУ Kyocera EcoSys M5526cdn",
    "component_type": "cartridge",
    "component_color": "Синий (Cyan)",
    "cartridge_model": "Kyocera TK-5240C",
    "detection_source": "database",
    "printer_is_color": true,
    "cartridge_color": "Синий (Cyan)",
    "db_name": "ITINVENT",
    "timestamp": "2026-02-10T15:07:15.616394",
    "model_name": "МФУ Kyocera EcoSys M5526cdn"
  },
  {
    "branch": "г.Тюмень, Первомайская 21",
    "location": "21_205",
    "printer_model": "МФУ Kyocera EcoSys M5526cdn",
    "component_type": "cartridge",
    "component_color": "Синий (Cyan)",
    "cartridge_model": "Kyocera TK-5240C",
    "detection_source": "database",
    "printer_is_color": true,
    "cartridge_color": "Синий (Cyan)",
    "db_name": "ITINVENT",
    "timestamp": "2026-02-10T15:07:15.616394"
  },
  {
    "serial_no": "PC1NAEES",
    "hw_serial_no": null,
    "model_name": "Lenovo ThinkCentre M720q",
    "manufacturer": "Lenovo",
    "branch": "г.Тюмень, Первомайская 19",
    "location": "19_307",
    "employee": "Хомиченко Ксения Юрьевна",
    "inv_no": "102775.0",
    "db_name": "ITINVENT",
    "timestamp": "2026-02-18T14:39:00.554886",
    "serial_number": "PC1NAEES"
  },
  {
    "serial_no": "PC1NAEES",
    "hw_serial_no": null,
    "model_name": "Lenovo ThinkCentre M720q",
    "manufacturer": "Lenovo",
    "branch": "г.Тюмень, Первомайская 19",
    "location": "19_307",
    "employee": "Хомиченко Ксения Юрьевна",
    "inv_no": 102775.0,
    "db_name": "ITINVENT",
    "timestamp": "2026-02-18T14:39:00.554886"
  },
  {
    "serial_no": "DB24933",
    "hw_serial_no": null,
    "model_name": "Dell Vostro 3888",
    "manufacturer": "Dell",
    "branch": "г.Тюмень, Первомайская 19",
    "location": "19_206",
    "employee": "Токарева Елена Александровна",
    "inv_no": "100152.0",
    "db_name": "ITINVENT",
    "timestamp": "2026-02-18T14:38:49.212514",
    "serial_number": "DB24933"
  },
  {
    "serial_no": "DB24933",
    "hw_serial_no": null,
    "model_name": "Dell Vostro 3888",
    "manufacturer": "Dell",
    "branch": "г.Тюмень, Первомайская 19",
    "location": "19_206",
    "employee": "Токарева Елена Александровна",
    "inv_no": 100152.0,
    "db_name": "ITINVENT",
    "timestamp": "2026-02-18T14:38:49.212514"
  },
  {
    "serial_no": "109V38L0C019",
    "hw_serial_no": null,
    "model_name": "AirTone",
    "manufacturer": "AirTone",
    "branch": "г.Тюмень, Первомайская 19",
    "location": "19_305",
    "employee": "Волкова Ольга Сергеевна",
    "inv_no": "101262.0",
    "db_name": "ITINVENT",
    "timestamp": "2026-02-19T15:54:32.983949",
    "serial_number": "109V38L0C019"
  },
  {
    "serial_no": "109V38L0C019",
    "hw_serial_no": null,
    "model_name": "AirTone",
    "manufacturer": "AirTone",
    "branch": "г.Тюмень, Первомайская 19",
    "location": "19_305",
    "employee": "Волкова Ольга Сергеевна",
    "inv_no": 101262.0,
    "db_name": "ITINVENT",
    "timestamp": "2026-02-19T15:54:32.983949"
  },
  {
    "serial_no": "H43S9W2",
    "hw_serial_no": null,
    "model_name": "Dell Vostro 3470",
    "manufacturer": "Dell",
    "branch": "г.Тюмень, Первомайская 19",
    "location": "19_305",
    "employee": "Бабушкина Олеся Александровна",
    "inv_no": "101864.0",
    "db_name": "ITINVENT",
    "timestamp": "2026-02-19T15:54:05.472615",
    "serial_number": "H43S9W2"
  },
  {
    "serial_no": "H43S9W2",
    "hw_serial_no": null,
    "model_name": "Dell Vostro 3470",
    "manufacturer": "Dell",
    "branch": "г.Тюмень, Первомайская 19",
    "location": "19_305",
    "employee": "Бабушкина Олеся Александровна",
    "inv_no": 101864.0,
    "db_name": "ITINVENT",
    "timestamp": "2026-02-19T15:54:05.472615"
  },
  {
    "serial_no": "CZC022B4P9",
    "hw_serial_no": null,
    "model_name": "HP ProDesk 400 G6 MT",
    "manufacturer": "HP",
    "branch": "г.Тюмень, Первомайская 19",
    "location": "19_305",
    "employee": "Пылаева Виктория Викторовна",
    "inv_no": "101552.0",
    "db_name": "ITINVENT",
    "timestamp": "2026-02-19T15:53:33.305568",
    "serial_number": "CZC022B4P9"
  },
  {
    "serial_no": "CZC022B4P9",
    "hw_serial_no": null,
    "model_name": "HP ProDesk 400 G6 MT",
    "manufacturer": "HP",
    "branch": "г.Тюмень, Первомайская 19",
    "location": "19_305",
    "employee": "Пылаева Виктория Викторовна",
    "inv_no": 101552.0,
    "db_name": "ITINVENT",
    "timestamp": "2026-02-19T15:53:33.305568"
  },
  {
    "serial_no": "PC1TGTLS",
    "hw_serial_no": null,
    "model_name": "Lenovo ThinkCentre M720q",
    "manufacturer": "Lenovo",
    "branch": "г.Тюмень, Первомайская 19",
    "location": "19_304",
    "employee": "Каменских Юлия Васильевна",
    "inv_no": "100156.0",
    "db_name": "ITINVENT",
    "timestamp": "2026-02-19T15:53:16.258793",
    "serial_number": "PC1TGTLS"
  },
  {
    "serial_no": "PC1TGTLS",
    "hw_serial_no": null,
    "model_name": "Lenovo ThinkCentre M720q",
    "manufacturer": "Lenovo",
    "branch": "г.Тюмень, Первомайская 19",
    "location": "19_304",
    "employee": "Каменских Юлия Васильевна",
    "inv_no": 100156.0,
    "db_name": "ITINVENT",
    "timestamp": "2026-02-19T15:53:16.258793"
  }
]